navibridge/__init__.py
navibridge/api/__init__.py
navibridge/api/ansys_api.py
navibridge/api/ansys_task.py
navibridge/api/ansys_tools.py
navibridge/api/base_api.py
navibridge/api/midas_api.py
navibridge/api/wind_calculation.py
navibridge/fem_base/__init__.py
navibridge/fem_base/base.py
navibridge/fem_base/element.py
navibridge/fem_base/fix.py
navibridge/fem_base/material.py
navibridge/fem_base/node.py
navibridge/fem_base/section.py
navibridge/tools/__init__.py
navibridge/zoo/__init__.py
navibridge/zoo/fem.py
navibridge/zoo/section_group.py
navibridge/zoo/tower.py
navibridge/zoo/truss.py
test/test.py
navibridge-0.2.6.dist-info/METADATA
navibridge-0.2.6.dist-info/WHEEL
navibridge-0.2.6.dist-info/top_level.txt
navibridge-0.2.6.dist-info/RECORD
