Metadata-Version: 2.1
Name: navibridge
Version: 0.2.6
Summary: A navigation bridge modeler
Author-email: BillHu <billhu0228@icloud.com>
Maintainer-email: BillHu <billhu0228@icloud.com>
Project-URL: homepage, https://github.com/billhu0228/NavigationBridgeModeler
Project-URL: repository, https://github.com/billhu0228/NavigationBridgeModeler
Requires-Dist: ezdxf>=1.3.0
Requires-Dist: numpy>=1.21.0
Requires-Dist: Pint>=0.20.0
Requires-Dist: scipy>=1.0.0
Requires-Dist: pandas>=2.0.0
Requires-Dist: PyAngle>=2.0.0
